<?xml version='1.0' encoding='utf-8'?>
<likuciai><row><kodas>29404</kodas><I17_KIEKIS>100</I17_KIEKIS></row><row><kodas>53420</kodas><I17_KIEKIS>100</I17_KIEKIS></row><row><kodas>53490</kodas><I17_KIEKIS>100</I17_KIEKIS></row><row><kodas>71992</kodas><I17_KIEKIS>0</I17_KIEKIS></row><row><kodas>72370</kodas><I17_KIEKIS>0</I17_KIEKIS></row><row><kodas>74471</kodas><I17_KIEKIS>100</I17_KIEKIS></row><row><kodas>78658</kodas><I17_KIEKIS>20</I17_KIEKIS></row><row><kodas>78734</kodas><I17_KIEKIS>100</I17_KIEKIS></row><row><kodas>78736</kodas><I17_KIEKIS>100</I17_KIEKIS></row><row><kodas>79782</kodas><I17_KIEKIS>100</I17_KIEKIS></row><row><kodas>81830</kodas><I17_KIEKIS>0</I17_KIEKIS></row><row><kodas>82015</kodas><I17_KIEKIS>100</I17_KIEKIS></row><row><kodas>82021</kodas><I17_KIEKIS>100</I17_KIEKIS></row><row><kodas>82107</kodas><I17_KIEKIS>100</I17_KIEKIS></row><row><kodas>82967</kodas><I17_KIEKIS>20</I17_KIEKIS></row><row><kodas>88680</kodas><I17_KIEKIS>100</I17_KIEKIS></row><row><kodas>89101</kodas><I17_KIEKIS>0</I17_KIEKIS></row><row><kodas>89331</kodas><I17_KIEKIS>100</I17_KIEKIS></row><row><kodas>YG-00263</kodas><I17_KIEKIS>100</I17_KIEKIS></row><row><kodas>YT-05345</kodas><I17_KIEKIS>100</I17_KIEKIS></row><row><kodas>YT-0596</kodas><I17_KIEKIS>100</I17_KIEKIS></row><row><kodas>YT-0617</kodas><I17_KIEKIS>20</I17_KIEKIS></row><row><kodas>YT-0653</kodas><I17_KIEKIS>100</I17_KIEKIS></row><row><kodas>YT-06845</kodas><I17_KIEKIS>100</I17_KIEKIS></row><row><kodas>YT-06881</kodas><I17_KIEKIS>100</I17_KIEKIS></row><row><kodas>YT-08144</kodas><I17_KIEKIS>100</I17_KIEKIS></row><row><kodas>YT-08920</kodas><I17_KIEKIS>0</I17_KIEKIS></row><row><kodas>YT-09061</kodas><I17_KIEKIS>0</I17_KIEKIS></row><row><kodas>YT-09615</kodas><I17_KIEKIS>20</I17_KIEKIS></row><row><kodas>YT-12681</kodas><I17_KIEKIS>100</I17_KIEKIS></row><row><kodas>YT-20957</kodas><I17_KIEKIS>100</I17_KIEKIS></row><row><kodas>YT-24209</kodas><I17_KIEKIS>100</I17_KIEKIS></row><row><kodas>YT-25030</kodas><I17_KIEKIS>100</I17_KIEKIS></row><row><kodas>YT-36011</kodas><I17_KIEKIS>100</I17_KIEKIS></row><row><kodas>YT-37450</kodas><I17_KIEKIS>100</I17_KIEKIS></row><row><kodas>YT-38561</kodas><I17_KIEKIS>100</I17_KIEKIS></row><row><kodas>YT-3895</kodas><I17_KIEKIS>20</I17_KIEKIS></row><row><kodas>YT-46270</kodas><I17_KIEKIS>100</I17_KIEKIS></row><row><kodas>YT-47197</kodas><I17_KIEKIS>100</I17_KIEKIS></row><row><kodas>YT-5533</kodas><I17_KIEKIS>20</I17_KIEKIS></row><row><kodas>YT-5537</kodas><I17_KIEKIS>20</I17_KIEKIS></row><row><kodas>YT-55600</kodas><I17_KIEKIS>0</I17_KIEKIS></row><row><kodas>YT-61025</kodas><I17_KIEKIS>100</I17_KIEKIS></row><row><kodas>YT-65049</kodas><I17_KIEKIS>20</I17_KIEKIS></row><row><kodas>YT-730933</kodas><I17_KIEKIS>100</I17_KIEKIS></row><row><kodas>YT-80070</kodas><I17_KIEKIS>100</I17_KIEKIS></row><row><kodas>YT-80080</kodas><I17_KIEKIS>100</I17_KIEKIS></row><row><kodas>YT-81052</kodas><I17_KIEKIS>100</I17_KIEKIS></row><row><kodas>YT-81355</kodas><I17_KIEKIS>20</I17_KIEKIS></row><row><kodas>YT-821024</kodas><I17_KIEKIS>100</I17_KIEKIS></row><row><kodas>YT-82813</kodas><I17_KIEKIS>20</I17_KIEKIS></row><row><kodas>YT-84797</kodas><I17_KIEKIS>0</I17_KIEKIS></row><row><kodas>YT-84872</kodas><I17_KIEKIS>0</I17_KIEKIS></row><row><kodas>YT-85192</kodas><I17_KIEKIS>20</I17_KIEKIS></row><row><kodas>YT-86704</kodas><I17_KIEKIS>20</I17_KIEKIS></row></likuciai>